githubranger/__init__.py
githubranger/helpers.py
githubranger/org.py
githubranger/repo.py
githubranger/token.py
githubranger/user.py
githubranger/util.py
githubranger-2025.6.0.dist-info/METADATA
githubranger-2025.6.0.dist-info/WHEEL
githubranger-2025.6.0.dist-info/licenses/LICENSE
githubranger-2025.6.0.dist-info/RECORD
