Metadata-Version: 2.4
Name: githubranger
Version: 2025.6.0
Summary: Python package for managing and automating tasks across multiple GitHub repositories.
Project-URL: Repository, https://github.com/teachnology/githubranger
Author-email: Marijan Beg <m.beg@imperial.ac.uk>
License-Expression: MIT
License-File: LICENSE
Keywords: automation,github,higher education,repositories
Classifier: Development Status :: 5 - Production/Stable
Classifier: Intended Audience :: Education
Classifier: License :: OSI Approved :: MIT License
Classifier: Natural Language :: English
Classifier: Operating System :: OS Independent
Requires-Python: >=3.13
Requires-Dist: pandas>=2.2.3
Requires-Dist: requests>=2.32.3
Requires-Dist: tqdm>=4.67.1
